LICENSE
MANIFEST.in
README.rst
setup.py
antispam/__init__.py
antispam/admin.py
antispam/apps.py
antispam/context_processors.py
antispam/decorators.py
antispam/helpers.py
antispam/middlewares.py
antispam/models.py
antispam/views.py
antispam/management/__inti__.py
antispam/management/commands/__init__.py
antispam/management/commands/exportspamips.py
antispam/management/commands/importspamips.py
antispam/management/commands/__pycache__/__init__.cpython-34.pyc
antispam/management/commands/__pycache__/exportspamips.cpython-34.pyc
antispam/management/commands/__pycache__/importspamips.cpython-34.pyc
antispam/migrations/0001_initial.py
antispam/migrations/0002_ipacesslog.py
antispam/migrations/__init__.py
antispam/migrations/__pycache__/0001_initial.cpython-34.pyc
antispam/migrations/__pycache__/0002_ipacesslog.cpython-34.pyc
antispam/migrations/__pycache__/__init__.cpython-34.pyc
crimson_antispam.egg-info/PKG-INFO
crimson_antispam.egg-info/SOURCES.txt
crimson_antispam.egg-info/dependency_links.txt
crimson_antispam.egg-info/top_level.txt